fastmcp_http/__init__.py
fastmcp_http/__init__.pyi
fastmcp_http/client.py
fastmcp_http/client.pyi
fastmcp_http/server.py
fastmcp_http/server.pyi
fastmcp_http-0.1.4.dist-info/METADATA
fastmcp_http-0.1.4.dist-info/WHEEL
fastmcp_http-0.1.4.dist-info/top_level.txt
fastmcp_http-0.1.4.dist-info/RECORD
