Metadata-Version: 2.1
Name: fastmcp_http
Version: 0.1.4
Summary: FastMCP services via HTTP.
Author-email: Aradrareness <38016746+ARadRareness@users.noreply.github.com>
License: MIT
Project-URL: Homepage, https://github.com/ARadRareness/mcp-registry
Classifier: Programming Language :: Python :: 3
Classifier: License :: OSI Approved :: MIT License
Classifier: Operating System :: OS Independent
Requires-Python: >=3.6
Requires-Dist: requests
Requires-Dist: mcp>=1.2.0rc1
Requires-Dist: flask[async]
